{
  "items": [
    {
      "UPC": "012000001234",
      "Name": "Vanilla Syrup",
      "Category": "Syrup",
      "Size": "750ml",
      "Unit": "bottle",
      "Par": 6,
      "Qty": 4,
      "Notes": "Monin style",
      "Last_Added": "",
      "Last_Used": ""
    },
    {
      "UPC": "012000001235",
      "Name": "Caramel Syrup",
      "Category": "Syrup",
      "Size": "750ml",
      "Unit": "bottle",
      "Par": 6,
      "Qty": 5,
      "Notes": "Monin style",
      "Last_Added": "",
      "Last_Used": ""
    },
    {
      "UPC": "012000001236",
      "Name": "Hazelnut Syrup",
      "Category": "Syrup",
      "Size": "750ml",
      "Unit": "bottle",
      "Par": 6,
      "Qty": 2,
      "Notes": "Sugar-free",
      "Last_Added": "",
      "Last_Used": ""
    },
    {
      "UPC": "012000001237",
      "Name": "White Chocolate Syrup",
      "Category": "Syrup",
      "Size": "750ml",
      "Unit": "bottle",
      "Par": 6,
      "Qty": 3,
      "Notes": "",
      "Last_Added": "",
      "Last_Used": ""
    },
    {
      "UPC": "012000001238",
      "Name": "Brown Sugar Syrup",
      "Category": "Syrup",
      "Size": "750ml",
      "Unit": "bottle",
      "Par": 3,
      "Qty": 1,
      "Notes": "",
      "Last_Added": "",
      "Last_Used": ""
    },
    {
      "UPC": "041383093287",
      "Name": "Whole Milk",
      "Category": "Milk",
      "Size": "Gallon",
      "Unit": "jug",
      "Par": 4,
      "Qty": 2,
      "Notes": "Dairy",
      "Last_Added": "",
      "Last_Used": ""
    },
    {
      "UPC": "041383093288",
      "Name": "Oat Milk",
      "Category": "Milk",
      "Size": "64oz",
      "Unit": "carton",
      "Par": 6,
      "Qty": 4,
      "Notes": "Non-dairy",
      "Last_Added": "",
      "Last_Used": ""
    },
    {
      "UPC": "041383093289",
      "Name": "Almond Milk",
      "Category": "Milk",
      "Size": "64oz",
      "Unit": "carton",
      "Par": 6,
      "Qty": 3,
      "Notes": "Non-dairy",
      "Last_Added": "",
      "Last_Used": ""
    },
    {
      "UPC": "078742349812",
      "Name": "Whipped Cream",
      "Category": "Topping",
      "Size": "13oz",
      "Unit": "can",
      "Par": 6,
      "Qty": 5,
      "Notes": "",
      "Last_Added": "",
      "Last_Used": ""
    },
    {
      "UPC": "078742349813",
      "Name": "Caramel Drizzle",
      "Category": "Topping",
      "Size": "16oz",
      "Unit": "squeeze",
      "Par": 3,
      "Qty": 1,
      "Notes": "",
      "Last_Added": "",
      "Last_Used": ""
    },
    {
      "UPC": "078742349814",
      "Name": "Chocolate Drizzle",
      "Category": "Topping",
      "Size": "16oz",
      "Unit": "squeeze",
      "Par": 3,
      "Qty": 2,
      "Notes": "",
      "Last_Added": "",
      "Last_Used": ""
    },
    {
      "UPC": "012345678901",
      "Name": "16oz Hot Cups",
      "Category": "Cup",
      "Size": "16oz",
      "Unit": "case",
      "Par": 4,
      "Qty": 2,
      "Notes": "50-count sleeves",
      "Last_Added": "",
      "Last_Used": ""
    },
    {
      "UPC": "012345678902",
      "Name": "24oz Cold Cups",
      "Category": "Cup",
      "Size": "24oz",
      "Unit": "case",
      "Par": 4,
      "Qty": 3,
      "Notes": "50-count sleeves",
      "Last_Added": "",
      "Last_Used": ""
    },
    {
      "UPC": "012345678903",
      "Name": "Dome Lids",
      "Category": "Cup",
      "Size": "24oz",
      "Unit": "case",
      "Par": 4,
      "Qty": 1,
      "Notes": "For frappes",
      "Last_Added": "",
      "Last_Used": ""
    },
    {
      "UPC": "098765432111",
      "Name": "Espresso Beans",
      "Category": "Other",
      "Size": "5lb",
      "Unit": "bag",
      "Par": 6,
      "Qty": 3,
      "Notes": "Medium roast",
      "Last_Added": "",
      "Last_Used": ""
    },
    {
      "UPC": "098765432112",
      "Name": "Chai Concentrate",
      "Category": "Other",
      "Size": "32oz",
      "Unit": "bottle",
      "Par": 4,
      "Qty": 2,
      "Notes": "",
      "Last_Added": "",
      "Last_Used": ""
    }
  ]
}
